gitsniff/__init__.py
gitsniff/main.py
gitsniff-1.0.2.dist-info/licenses/LICENCE
gitsniff-1.0.2.dist-info/METADATA
gitsniff-1.0.2.dist-info/WHEEL
gitsniff-1.0.2.dist-info/entry_points.txt
gitsniff-1.0.2.dist-info/top_level.txt
gitsniff-1.0.2.dist-info/RECORD
