Metadata-Version: 2.4
Name: gitsniff
Version: 1.0.2
Summary: GitHub Email Scanner for OSINT - Extract emails from repositories and user events
Author-email: WKoA <reginaldgillespie@protonmail.com>
Maintainer-email: WKoA <reginaldgillespie@protonmail.com>
License: MIT
Project-URL: Homepage, https://github.com/Reginald-Gillespie/GitSniff
Project-URL: Documentation, https://github.com/Reginald-Gillespie/GitSniff#readme
Project-URL: Repository, https://github.com/Reginald-Gillespie/GitSniff
Project-URL: Bug Tracker, https://github.com/Reginald-Gillespie/GitSniff/issues
Keywords: github,osint,email,scanner,reconnaissance,git
Classifier: Development Status :: 4 - Beta
Classifier: Environment :: Console
Classifier: Intended Audience :: Information Technology
Classifier: Intended Audience :: System Administrators
Classifier: License :: OSI Approved :: MIT License
Classifier: Operating System :: OS Independent
Classifier: Programming Language :: Python :: 3
Classifier: Programming Language :: Python :: 3.8
Classifier: Programming Language :: Python :: 3.9
Classifier: Programming Language :: Python :: 3.10
Classifier: Programming Language :: Python :: 3.11
Classifier: Programming Language :: Python :: 3.12
Classifier: Topic :: Security
Classifier: Topic :: Utilities
Requires-Python: >=3.8
License-File: LICENCE
Requires-Dist: requests>=2.25.0
Requires-Dist: rich>=10.0.0
Provides-Extra: dev
Requires-Dist: pytest>=6.0; extra == "dev"
Requires-Dist: pytest-cov>=2.0; extra == "dev"
Requires-Dist: black>=21.0; extra == "dev"
Requires-Dist: flake8>=3.8; extra == "dev"
Requires-Dist: mypy>=0.800; extra == "dev"
Requires-Dist: pre-commit>=2.0; extra == "dev"
Dynamic: license-file
